setup.py
introspectionparser/__init__.py
introspectionparser.egg-info/PKG-INFO
introspectionparser.egg-info/SOURCES.txt
introspectionparser.egg-info/dependency_links.txt
introspectionparser.egg-info/entry_points.txt
introspectionparser.egg-info/requires.txt
introspectionparser.egg-info/top_level.txt