Metadata-Version: 1.1
Name: introspectionparser
Version: 0.1
Summary: Parses introspection json output to OpenStack prettytable form
Home-page: https://github.com/ervikrant06/Parse_json_introspection_data
Author: Vikrant Aggarwal
Author-email: vaggarwa@redhat.com
License: UNKNOWN
Platform: Linux
Classifier: Development Status :: 4 - Beta
Classifier: License :: OSI Approved :: GNU General Public License v3 (GPLv3)
Classifier: Programming Language :: Python :: 2.7
Classifier: Programming Language :: Python :: 3.5
Classifier: Topic :: Text Editors :: Text Processing
Classifier: Topic :: Text Processing :: Markup :: XML
